aioheos/__init__.py
aioheos/aioheos.py
aioheos/aioheoscontroller.py
aioheos/aioheosgroup.py
aioheos/aioheosplayer.py
aioheos/aioheosupnp.py
aioheos/version.py
aioheos-0.4.0.dist-info/LICENSE
aioheos-0.4.0.dist-info/METADATA
aioheos-0.4.0.dist-info/WHEEL
aioheos-0.4.0.dist-info/top_level.txt
aioheos-0.4.0.dist-info/RECORD
