Metadata-Version: 2.1
Name: aioheos
Version: 0.4.0
Summary: Denon HEOS
Home-page: http://github.com/easink/aioheos
Author: Andreas Rydbrink
Author-email: andreas.rydbrink@gmail.com
License: MIT
Platform: UNKNOWN
Classifier: Programming Language :: Python :: 3
Classifier: License :: OSI Approved :: MIT License
Classifier: Operating System :: OS Independent
Requires-Dist: aiohttp
Requires-Dist: lxml
Requires-Dist: pytz
